{
    "login": {
        "title": "ඇතුළු වන්න",
        "username": "පරිශීලක නාමය",
        "password": "මුරපදය",
        "button": "ඇතුළු වන්න",
        "noAccount": "ගිණුමක් නැද්ද?",
        "register": "ලියාපදිංචි වන්න"
    },
    "register": {
        "title": "ලියාපදිංචි වන්න",
        "username": "පරිශීලක නාමය",
        "email": "ඊමේල්",
        "password": "මුරපදය",
        "confirmPassword": "මුරපදය තහවුරු කරන්න",
        "button": "ලියාපදිංචි වන්න",
        "haveAccount": "දැනටමත් ගිණුමක් තිබේද?",
        "login": "ඇතුළු වන්න"
    },
    "home": {
        "welcome": "ආයුබෝවන්!",
        "description": "ඔබගේ ගොවිපළ කළමනාකරණය පහසු කරගන්න."
    },
    "dashboard": {
        "title": "පුවරුව",
        "overview": "දළ විශ්ලේෂණය",
        "crops": "බෝග",
        "weather": "කාලගුණය",
        "tasks": "කාර්යයන්"
    },
    "profile": {
        "title": "පැතිකඩ",
        "edit": "සංස්කරණය කරන්න",
        "logout": "පිටවීම"
    }
}